repositoryupdater/__init__.py
repositoryupdater/__main__.py
repositoryupdater/addon.py
repositoryupdater/cli.py
repositoryupdater/const.py
repositoryupdater/github.py
repositoryupdater/repository.py
repository_updater-1.3.0.dist-info/LICENSE.md
repository_updater-1.3.0.dist-info/METADATA
repository_updater-1.3.0.dist-info/WHEEL
repository_updater-1.3.0.dist-info/entry_points.txt
repository_updater-1.3.0.dist-info/top_level.txt
repository_updater-1.3.0.dist-info/RECORD
