Metadata-Version: 2.1
Name: repository-updater
Version: 1.3.0
Home-page: https://github.com/hassio-addons/repository-updater
Author: Franck Nijhof
Author-email: frenck@addons.community
License: MIT
Keywords: addons,repository,home assistant,home-assistant,add-ons,frenck
Platform: any
Classifier: Environment :: Console
Classifier: Intended Audience :: Developers
Classifier: License :: OSI Approved :: MIT License
Classifier: Programming Language :: Python
Classifier: Programming Language :: Python :: 3.8
Classifier: Programming Language :: Python :: 3.9
Classifier: Programming Language :: Python :: 3.10
Classifier: Programming Language :: Python :: 3
Classifier: Topic :: Software Development :: Build Tools
Classifier: Topic :: Utilities
License-File: LICENSE.md
Requires-Dist: click (==8.1.5)
Requires-Dist: crayons (==0.4.0)
Requires-Dist: emoji (==2.6.0)
Requires-Dist: GitPython (==3.1.32)
Requires-Dist: Jinja2 (==3.1.2)
Requires-Dist: PyGithub (==1.59.0)
Requires-Dist: python-dateutil (==2.8.2)
Requires-Dist: PyYAML (==6.0.1)
Requires-Dist: semver (==3.0.1)
